README
setup.py
hpgl/__init__.py
hpgl/cli.py
hpgl/fonts.py
hpgl/hpgl.py
hpgl/hprtl.py
hpgl/version.py
python_hpgl.egg-info/PKG-INFO
python_hpgl.egg-info/SOURCES.txt
python_hpgl.egg-info/dependency_links.txt
python_hpgl.egg-info/entry_points.txt
python_hpgl.egg-info/top_level.txt