Metadata-Version: 1.1
Name: python-hpgl
Version: 0.1.0
Summary: HPGL parsing library
Home-page: http://alexforencich.com/wiki/en/python-hpgl/start
Author: Alex Forencich
Author-email: alex@alexforencich.com
License: MIT License
Download-URL: http://github.com/alexforencich/python-hpgl/tarball/master
Keywords: HPGL
Platform: UNKNOWN
Classifier: Development Status :: 4 - Beta
Classifier: Environment :: Console
Classifier: License :: OSI Approved :: MIT License
Classifier: Natural Language :: English
Classifier: Operating System :: OS Independent
Classifier: Intended Audience :: Science/Research
Classifier: Topic :: Multimedia :: Graphics :: Graphics Conversion
Classifier: Topic :: Printing
Classifier: Topic :: Scientific/Engineering :: Interface Engine/Protocol Translator
Classifier: Topic :: Software Development :: Libraries :: Python Modules
Classifier: Programming Language :: Python :: 2
Classifier: Programming Language :: Python :: 3
